diffusion/__init__.py
diffusion/base.py
diffusion/data.py
diffusion/distribution.py
diffusion/guidance.py
diffusion/loss.py
diffusion/net.py
diffusion/noise.py
diffusion/schedule.py
diffusion/time.py
diffusion/utils/nn/__init__.py
diffusion/utils/nn/functional.py
docs/node_modules/katex/src/fonts/generate_fonts.py
docs/node_modules/katex/src/metrics/extract_tfms.py
docs/node_modules/katex/src/metrics/extract_ttfs.py
docs/node_modules/katex/src/metrics/format_json.py
docs/node_modules/katex/src/metrics/parse_tfm.py
examples/conditional-diffusion.py
examples/embedding-diffusion.py
examples/text-diffusion.py
examples/transformer-diffusion.py
examples/unconditional-diffusion.py
examples/utils/__init__.py
modular_diffusion-0.0.3.dist-info/METADATA
modular_diffusion-0.0.3.dist-info/WHEEL
modular_diffusion-0.0.3.dist-info/licenses/LICENSE
modular_diffusion-0.0.3.dist-info/RECORD
