Metadata-Version: 2.1
Name: modular-diffusion
Version: 0.0.3
Summary: Modular Diffusion
Project-URL: Homepage, https://github.com/cabralpinto/modular-diffusion
Project-URL: Bug Tracker, https://github.com/cabralpinto/modular-diffusion/issues
Author-email: João Cabral Pinto <jmcabralpinto@gmail.com>
License-File: LICENSE
Classifier: License :: OSI Approved :: MIT License
Classifier: Operating System :: OS Independent
Classifier: Programming Language :: Python :: 3
Requires-Python: >=3.10
Requires-Dist: einops==0.6.1
Requires-Dist: tqdm==4.64.1
Requires-Dist: typing-extensions==4.7.1
